libtorrent.so
python_libtorrent_bin-2.0.2.dist-info/METADATA
python_libtorrent_bin-2.0.2.dist-info/RECORD
python_libtorrent_bin-2.0.2.dist-info/top_level.txt
python_libtorrent_bin-2.0.2.dist-info/WHEEL
python_libtorrent_bin.libs/libboost_python38-104d2cb2.so.1.73.0
