Metadata-Version: 2.1
Name: python-libtorrent-bin
Version: 2.0.2
Summary: unofficial prebuilt binaries for Python bindings for libtorrent-rasterbar
Home-page: http://libtorrent.org
Author: Arvid Norberg
Author-email: arvid@libtorrent.org
License: BSD
Platform: Linux-x86_64
